aart/__init__.py
aart/ellipi_f.py
aart/gfactor.py
aart/iImages.py
aart/iMovies.py
aart/intensity_f.py
aart/lensingbands.py
aart/misc.py
aart/mkplot.py
aart/parameters.py
aart/polarization.py
aart/polarization_f.py
aart/radialfit.py
aart/radialintensity.py
aart/raytracing.py
aart/raytracing_f.py
aart/rprofs_f.py
aart/visamp.py
aart/visamp_f.py
aart-2.1.10.dist-info/licenses/LICENSE.txt
aart-2.1.10.dist-info/METADATA
aart-2.1.10.dist-info/WHEEL
aart-2.1.10.dist-info/top_level.txt
aart-2.1.10.dist-info/RECORD
