Metadata-Version: 2.4
Name: aart
Version: 2.1.10
Summary: An adaptive analytical ray-tracing code to study black hole photon rings
Author-email: "Alejandro Cardenas-Avendano, Alex Lupsasca & Hengrui Zhu" <cardenas@wfu.edu>
Project-URL: Homepage, https://github.com/iAART/aart
Classifier: Programming Language :: Python :: 3
Classifier: License :: OSI Approved :: MIT License
Classifier: Operating System :: OS Independent
Requires-Python: >=3.7
License-File: LICENSE.txt
Dynamic: license-file
